README.txt
setup.cfg
setup.py
tx/__init__.py
tx.tinymce_linguaplone_patch.egg-info/PKG-INFO
tx.tinymce_linguaplone_patch.egg-info/SOURCES.txt
tx.tinymce_linguaplone_patch.egg-info/dependency_links.txt
tx.tinymce_linguaplone_patch.egg-info/entry_points.txt
tx.tinymce_linguaplone_patch.egg-info/namespace_packages.txt
tx.tinymce_linguaplone_patch.egg-info/not-zip-safe
tx.tinymce_linguaplone_patch.egg-info/paster_plugins.txt
tx.tinymce_linguaplone_patch.egg-info/requires.txt
tx.tinymce_linguaplone_patch.egg-info/top_level.txt
tx/tinymce_linguaplone_patch/__init__.py
tx/tinymce_linguaplone_patch/configure.zcml
tx/tinymce_linguaplone_patch/patches.py
tx/tinymce_linguaplone_patch/patches.zcml
tx/tinymce_linguaplone_patch/tests.py